geoapp/__init__.py
geoapp/common.py
geoapp/geoapp.py
geoapp-0.0.2.dist-info/licenses/LICENSE
geoapp-0.0.2.dist-info/METADATA
geoapp-0.0.2.dist-info/WHEEL
geoapp-0.0.2.dist-info/entry_points.txt
geoapp-0.0.2.dist-info/top_level.txt
geoapp-0.0.2.dist-info/RECORD
